CHANGES.rst
DESCRIPTION.rst
LICENSE
MANIFEST.in
README.md
setup.py
src/wai.annotations.tf.egg-info/PKG-INFO
src/wai.annotations.tf.egg-info/SOURCES.txt
src/wai.annotations.tf.egg-info/dependency_links.txt
src/wai.annotations.tf.egg-info/entry_points.txt
src/wai.annotations.tf.egg-info/namespace_packages.txt
src/wai.annotations.tf.egg-info/requires.txt
src/wai.annotations.tf.egg-info/top_level.txt
src/wai/annotations/tf/__init__.py
src/wai/annotations/tf/compat/__init__.py
src/wai/annotations/tf/compat/v1/__init__.py
src/wai/annotations/tf/compat/v1/_ensure_eager_execution.py
src/wai/annotations/tf/compat/v2/__init__.py
src/wai/annotations/tf/compat/v2/_ensure_eager_execution.py
src/wai/annotations/tf/component/_FromTensorflowExample.py
src/wai/annotations/tf/component/_TensorflowExampleReader.py
src/wai/annotations/tf/component/_TensorflowExampleWriter.py
src/wai/annotations/tf/component/_ToTensorflowExample.py
src/wai/annotations/tf/component/__init__.py
src/wai/annotations/tf/specifier/_TFRecordsInputFormatSpecifier.py
src/wai/annotations/tf/specifier/_TFRecordsOutputFormatSpecifier.py
src/wai/annotations/tf/specifier/__init__.py
src/wai/annotations/tf/utils/_LabelMapAccumulator.py
src/wai/annotations/tf/utils/__init__.py
src/wai/annotations/tf/utils/_dense_numerical_from_mask.py
src/wai/annotations/tf/utils/_ensure_available.py
src/wai/annotations/tf/utils/_extract_feature.py
src/wai/annotations/tf/utils/_format.py
src/wai/annotations/tf/utils/_image_info_from_example.py
src/wai/annotations/tf/utils/_make_feature.py
src/wai/annotations/tf/utils/_negative_example.py
src/wai/annotations/tf/utils/_png_from_mask.py
src/wai/annotations/tf/utils/_polygon_from_mask.py