Metadata-Version: 2.1
Name: wai.annotations.tf
Version: 1.1.0
Summary: Tensorflow format plugins for wai.annotations.
Home-page: https://github.com/waikato-datamining/wai-annotations-tf
Author: Corey Sterling
Author-email: coreytsterling@gmail.com
License: Apache License Version 2.0
Platform: UNKNOWN
Classifier: Development Status :: 4 - Beta
Classifier: License :: OSI Approved :: Apache Software License
Classifier: Topic :: Scientific/Engineering :: Mathematics
Classifier: Programming Language :: Python :: 3
